[
    {
        "id": "a226d8468674cb57",
        "type": "tab",
        "label": "Flow 1",
        "disabled": false,
        "info": "",
        "env": []
    },
    {
        "id": "aaf72add94e17b8b",
        "type": "inject",
        "z": "a226d8468674cb57",
        "name": "",
        "props": [
            {
                "p": "payload"
            },
            {
                "p": "topic",
                "vt": "str"
            }
        ],
        "repeat": "",
        "crontab": "",
        "once": false,
        "onceDelay": 0.1,
        "topic": "",
        "payload": "",
        "payloadType": "date",
        "x": 180,
        "y": 100,
        "wires": [
            [
                "d90b48217004e3b7"
            ]
        ]
    },
    {
        "id": "d90b48217004e3b7",
        "type": "debug",
        "z": "a226d8468674cb57",
        "name": "",
        "active": true,
        "tosidebar": true,
        "console": false,
        "tostatus": false,
        "complete": "false",
        "statusVal": "",
        "statusType": "auto",
        "x": 370,
        "y": 100,
        "wires": []
    }
]